{
    "locations": {
        "columns": {
            "name": [
                {
                    "name": "Wroclaw",
                    "type": "TEXT"
                },
                {
                    "name": "Klodzko",
                    "type": "TEXT"
                },
                {
                    "name": "Poznań",
                    "type": "TEXT"
                }
            ],
            "address": [
                {
                    "name": "Wybrzeże Stanisława Wyspiańskiego",
                    "type": "TEXT"
                }
            ]
        }
    },
    "clients": {
        "columns": {

        }
    },
    "bike_types": {
        "columns": {
            "name": [
                {
                    "name": "A cool Kross",
                    "type": "TEXT"
                },
                {
                    "name": "A very cool Merida MTB bikde",
                    "type": "TEXT"
                }
            ]
        }
    },
    "discounts": {
       
    },
    "bikes": {
        "columns": {
            "status": [
                {
                    "name": "active",
                    "type" : "TEXT"
                },
                {
                    "name": "disabled",
                    "type" : "TEXT"
                }
            ]
        }
    },
    "maintenance_logs": {
        "columns": {
            "description":[
                {
                    "name": "Broken steering wheel",
                    "type": "TEXT"
                }
            ]
        }
    },
    "bike_accessories": {
        "columns": {
            "name":[
                {
                    "name": "Helmet",
                    "type": "TEXT"
                },
                {
                    "name": "Lights",
                    "type": "TEXT"
                }
            ]
        }
    }
}